.travis.yml
NOTICE.txt
README.rst
bootstrap.py
buildout.cfg
eke.committees.sublime-project
setup.cfg
setup.py
travis.cfg
docs/HISTORY.txt
docs/INSTALL.txt
docs/LICENSE.txt
eke/__init__.py
eke.committees.egg-info/PKG-INFO
eke.committees.egg-info/SOURCES.txt
eke.committees.egg-info/dependency_links.txt
eke.committees.egg-info/entry_points.txt
eke.committees.egg-info/namespace_packages.txt
eke.committees.egg-info/not-zip-safe
eke.committees.egg-info/requires.txt
eke.committees.egg-info/top_level.txt
eke/committees/README.rst
eke/committees/__init__.py
eke/committees/config.py
eke/committees/configure.zcml
eke/committees/interfaces.py
eke/committees/testing.py
eke/committees/upgrades.py
eke/committees/upgrades.zcml
eke/committees/browser/__init__.py
eke/committees/browser/configure.zcml
eke/committees/browser/rdf.py
eke/committees/browser/views.py
eke/committees/browser/images/committee-folder.gif
eke/committees/browser/images/committee.gif
eke/committees/browser/templates/committee.pt
eke/committees/browser/templates/committeefolder.pt
eke/committees/content/__init__.py
eke/committees/content/committee.py
eke/committees/content/committeefolder.py
eke/committees/content/configure.zcml
eke/committees/profiles/default/catalog.xml
eke/committees/profiles/default/factorytool.xml
eke/committees/profiles/default/metadata.xml
eke/committees/profiles/default/rolemap.xml
eke/committees/profiles/default/types.xml
eke/committees/profiles/default/types/Committee.xml
eke/committees/profiles/default/types/Committee_Folder.xml
eke/committees/tests/__init__.py
eke/committees/tests/test_functional.py
eke/committees/tests/test_setup.py